rkviewer/.controller.py.un~
rkviewer/.events.py.un~
rkviewer/.forms.py.un~
rkviewer/.iodine.py.un~
rkviewer/.plugin_manage.py.un~
rkviewer/.view.py.un~
rkviewer/__init__.py
rkviewer/canvas/.canvas.py.un~
rkviewer/canvas/.data.py.un~
rkviewer/canvas/.elements.py.un~
rkviewer/canvas/__init__.py
rkviewer/canvas/canvas.py
rkviewer/canvas/canvas.py~
rkviewer/canvas/data.py
rkviewer/canvas/data.py~
rkviewer/canvas/elements.py
rkviewer/canvas/elements.py~
rkviewer/canvas/geometry.py
rkviewer/canvas/overlays.py
rkviewer/canvas/state.py
rkviewer/canvas/utils.py
rkviewer/config.py
rkviewer/controller.py
rkviewer/controller.py~
rkviewer/events.py
rkviewer/events.py~
rkviewer/forms.py
rkviewer/forms.py~
rkviewer/iodine.py
rkviewer/iodine.py~
rkviewer/main.py
rkviewer/mvc.py
rkviewer/mvc.py~
rkviewer/plugin/.api.py.un~
rkviewer/plugin/__init__.py
rkviewer/plugin/api.py
rkviewer/plugin/api.py~
rkviewer/plugin/canvas.py
rkviewer/plugin/classes.py
rkviewer/plugin/classes.py~
rkviewer/plugin/events.py
rkviewer/plugin_manage.py
rkviewer/plugin_manage.py~
rkviewer/resources/__init__.py
rkviewer/resources/AlignBottom_XP.png
rkviewer/resources/alignHorizCenter_XP.png
rkviewer/resources/alignHorizEqually_XP.png
rkviewer/resources/alignLeft_XP.png
rkviewer/resources/alignOnGrid_XP.png
rkviewer/resources/alignRight_XP.png
rkviewer/resources/alignTop_XP.png
rkviewer/resources/alignVertCenter_XP.png
rkviewer/resources/alignVertEqually_XP.png
rkviewer/resources/info-2-16.png
rkviewer/utils.py
rkviewer/utils.py~
rkviewer/view.py
rkviewer/view.py~
rkviewer_plugins/.captureSBML.py.un~
rkviewer_plugins/.eventPlugin1.py.swp
rkviewer_plugins/.eventPlugin1.py.un~
rkviewer_plugins/.eventPlugin2.py.un~
rkviewer_plugins/.eventPlugin3.py.un~
rkviewer_plugins/.exportSBML.py.un~
rkviewer_plugins/.nodeCountBar.py.un~
rkviewer_plugins/.simulateNetwork.py.un~
rkviewer_plugins/.simulateNetwork1.py.un~
rkviewer_plugins/.tellurium.py.un~
rkviewer_plugins/.testconcentrationapi.py.un~
coyote_gui-0.1b8.dist-info/entry_points.txt
coyote_gui-0.1b8.dist-info/WHEEL
coyote_gui-0.1b8.dist-info/METADATA
coyote_gui-0.1b8.dist-info/RECORD
