Metadata-Version: 2.1
Name: coyote-gui
Version: 0.1b8
Summary: Extensible visualization and editing tool for reaction networks.
Author: Gary Geng
Author-email: xiaog3@uw.edu
Requires-Python: >=3.7.1,<4.0.0
Classifier: Development Status :: 4 - Beta
Classifier: Intended Audience :: Developers
Classifier: Intended Audience :: Science/Research
Classifier: Operating System :: MacOS
Classifier: Operating System :: Microsoft :: Windows
Classifier: Operating System :: POSIX :: Linux
Classifier: Programming Language :: Python :: 3
Classifier: Programming Language :: Python :: 3.6
Classifier: Programming Language :: Python :: 3.7
Classifier: Programming Language :: Python :: 3.8
Classifier: Programming Language :: Python :: 3.9
Classifier: Topic :: Scientific/Engineering :: Visualization
Classifier: Topic :: Software Development :: Build Tools
Provides-Extra: sbml
Requires-Dist: commentjson (>=0.9.0,<0.10.0)
Requires-Dist: dataclasses (>=0.8,<0.9); python_version >= "3.6" and python_version < "3.7"
Requires-Dist: marshmallow (>=3.11.1,<4.0.0)
Requires-Dist: marshmallow-polyfield (>=5.10,<6.0)
Requires-Dist: networkx (>=2.5.1,<3.0.0); extra == "sbml"
Requires-Dist: pandas (>=1.3.0,<2.0.0); extra == "sbml"
Requires-Dist: python-libsbml (>=5.18.0,<6.0.0); extra == "sbml"
Requires-Dist: sbml2matlab (==1.2.3); extra == "sbml"
Requires-Dist: simplesbml (>=2.2.0,<3.0.0); extra == "sbml"
Requires-Dist: sortedcontainers (>=2.3.0,<3.0.0)
Requires-Dist: tellurium (>=2.2.1,<3.0.0); extra == "sbml"
Requires-Dist: wxPython (==4.1.1)
